setup.py
flask_keyauth/__init__.py
flask_keyauth/keymanager.py
flask_keyauth/mongoaccountbroker.py
flask_keyauth.egg-info/PKG-INFO
flask_keyauth.egg-info/SOURCES.txt
flask_keyauth.egg-info/dependency_links.txt
flask_keyauth.egg-info/not-zip-safe
flask_keyauth.egg-info/top_level.txt