Metadata-Version: 1.1
Name: flask-keyauth
Version: 0.1.5
Summary: A module to simplify working with KEY auth in Flask apps
Home-page: http://www.github.com/jsevilleja/flask-keyauth
Author: Joel Sevilleja
Author-email: joel@jsevilleja.org
License: MIT
Platform: UNKNOWN
Classifier: Development Status :: 4 - Beta
Classifier: Intended Audience :: Developers
Classifier: Intended Audience :: System Administrators
Classifier: License :: OSI Approved :: MIT License
Classifier: Programming Language :: Python
Classifier: Topic :: Security
Classifier: Topic :: Software Development :: Libraries :: Python Modules
Requires: flask
Requires: pycrypto
